ppath/__init__.py
ppath/__init__.pyi
ppath-0.0.9.dist-info/LICENSE
ppath-0.0.9.dist-info/METADATA
ppath-0.0.9.dist-info/WHEEL
ppath-0.0.9.dist-info/top_level.txt
ppath-0.0.9.dist-info/RECORD
