Metadata-Version: 2.1
Name: ppath
Version: 0.0.9
Summary: Python Path
Author-email: José Antonio Puértolas Montañés <63794670+j5pu@users.noreply.github.com>
License: MIT
Project-URL: Homepage, https://github.com/j5pu/ppath
Requires-Python: >=3.11
License-File: LICENSE
Requires-Dist: pproj
Provides-Extra: dev
Requires-Dist: pproj[all] ; extra == 'dev'
